odoo8_addon_website_sale_category_megamenu-8.0.1.0.1.99.dev15-py2.7-nspkg.pth
odoo_addons/website_sale_category_megamenu/__openerp__.py
odoo_addons/website_sale_category_megamenu/__init__.py
odoo_addons/website_sale_category_megamenu/README.rst
odoo_addons/website_sale_category_megamenu/i18n/tr_TR.po
odoo_addons/website_sale_category_megamenu/i18n/pt.po
odoo_addons/website_sale_category_megamenu/i18n/it.po
odoo_addons/website_sale_category_megamenu/i18n/es.po
odoo_addons/website_sale_category_megamenu/i18n/bg.po
odoo_addons/website_sale_category_megamenu/i18n/sl.po
odoo_addons/website_sale_category_megamenu/i18n/de.po
odoo_addons/website_sale_category_megamenu/i18n/fr.po
odoo_addons/website_sale_category_megamenu/i18n/pt_BR.po
odoo_addons/website_sale_category_megamenu/i18n/fi.po
odoo_addons/website_sale_category_megamenu/views/layout.xml
odoo_addons/website_sale_category_megamenu/views/assets.xml
odoo_addons/website_sale_category_megamenu/static/description/icon.png
odoo_addons/website_sale_category_megamenu/static/src/js/frontend.js
odoo_addons/website_sale_category_megamenu/static/src/css/megamenu.css
odoo8_addon_website_sale_category_megamenu-8.0.1.0.1.99.dev15.dist-info/top_level.txt
odoo8_addon_website_sale_category_megamenu-8.0.1.0.1.99.dev15.dist-info/WHEEL
odoo8_addon_website_sale_category_megamenu-8.0.1.0.1.99.dev15.dist-info/RECORD
odoo8_addon_website_sale_category_megamenu-8.0.1.0.1.99.dev15.dist-info/metadata.json
odoo8_addon_website_sale_category_megamenu-8.0.1.0.1.99.dev15.dist-info/DESCRIPTION.rst
odoo8_addon_website_sale_category_megamenu-8.0.1.0.1.99.dev15.dist-info/METADATA
odoo8_addon_website_sale_category_megamenu-8.0.1.0.1.99.dev15.dist-info/namespace_packages.txt
