Metadata-Version: 2.0
Name: odoo8-addon-website-sale-category-megamenu
Version: 8.0.1.0.1.99.dev15
Summary: A megamenu to display product categories in the online shop
Home-page: http://www.antiun.com
Author: Antiun Ingeniería S.L., Odoo Community Association (OCA)
Author-email: support@odoo-community.org
License: AGPL-3
Platform: UNKNOWN
Requires-Dist: odoo (<9.0a,>=8.0a)
Classifier: Programming Language :: Python :: 2.7
Classifier: Framework :: Odoo
Classifier: License :: OSI Approved :: GNU Affero General Public License v3
